{
  "general": {
    "auto": true,
    "rate": 600,
    "rateSelector": [
      0,
      1,
      2
    ],
    "gripType": "tac:two_handed_ak47",
    "recoilAngle": 3.275,
    "horizontalRecoilAngle": 2.35,
    "recoilKick": 1.625,
    "recoilAdsReduction": 0.235,
    "weaponRecoilOffset": 0.625,
    "cameraRecoilModifier": 1.15,
    "recoilDuration": 0.195,
    "weightKilo": 4.4,

    "spread": 1.675,
    "firstShotSpread": 0.13,
    "hipFireInaccuracy": 6.25,
    "projToMinAccuracy": 6,
    "msToAccuracyReset": 130,
    "movementInaccuracy": 0.55
  },
  "projectile": {
    "item": "tac:762x39",
    "visible": false,
    "damage": 9,
    "size": 0.2,
    "speed": 19.5,
    "life": 12
  },
  "reloads": {
    "magFed": true,
    "maxAmmo": 30,
    "reloadMagTimer": 36,
    "additionalReloadEmptyMagTimer": 20,
    "maxAdditionalAmmoPerOC": [
      15,
      20,
      45
    ],
    "preReloadPauseTicks": 0
  },
  "sounds": {
    "fire": "tac:item.ak47_fire",
    "reloadNormal": "tac:animation.ak47_reload_norm",
    "reloadEmpty": "tac:animation.ak47_reload_empty",
    "draw": "tac:animation.ak47_draw",
    "inspect": "tac:animation.ak47_inspect",
    "cock": "tac:item.pistol.cock",
    "silencedFire": "tac:item.ak47_fire_s"
  },
  "display": {
    "flash": {
      "yOffset": 9.0,
      "zOffset": -20.75,
      "trailAdjust": 1.315,
      "size": 0.8
    }
  },
  "modules": {
    "zoom": {
      "fovModifier": 0.8,
      "yOffset": 11.075,
      "zOffset": -2.1
    },
    "attachments": {
      "barrel": {
        "yOffset": -100829.84,
        "zOffset": -11.55,
        "scale": 1.00
      },
      "stock": {
        "yOffset": 7.75,
        "zOffset": -22.05,
        "scale": 0.00
      },
      "scope": {
        "yOffset": 10.97,
        "zOffset": 4.6,
        "scale": 1.0
      }
    }
  }
}

