{"credit":"Made with Blockbench","textures":{"4":"tac:items/light_enfield_barrel"},"elements":[{"name":"octagon","from":[7.75083,8.96094,10.41016],"to":[8.24917,10.16406,14.27734],"shade":false,"rotation":{"angle":22.5,"axis":"z","origin":[8,9.5625,12.81641]},"faces":{"north":{"uv":[0,0,0.56954,1.375],"texture":"#4"},"east":{"uv":[4.5,1,10,2.375],"texture":"#4"},"south":{"uv":[0,0,0.56954,1.375],"texture":"#4"},"west":{"uv":[0,0,0,0],"texture":"#4"},"up":{"uv":[0,0,0.56954,5.5],"texture":"#4"},"down":{"uv":[0,0,0,0],"texture":"#4"}}},{"name":"octagon","from":[7.75083,8.96094,10.41016],"to":[8.24917,10.16406,14.27734],"shade":false,"rotation":{"angle":-22.5,"axis":"z","origin":[8,9.5625,12.81641]},"faces":{"north":{"uv":[0,0,0.56954,1.375],"texture":"#4"},"east":{"uv":[4.5,1,10,2.375],"texture":"#4"},"south":{"uv":[0,0,0.56954,1.375],"texture":"#4"},"west":{"uv":[0,0,0,0],"texture":"#4"},"up":{"uv":[0,0,0.56954,5.5],"texture":"#4"},"down":{"uv":[0,0,0,0],"texture":"#4"}}},{"name":"octagon","from":[7.39844,9.31333,10.41016],"to":[8.60156,9.81167,14.27734],"shade":false,"rotation":{"angle":22.5,"axis":"z","origin":[8,9.5625,12.81641]},"faces":{"north":{"uv":[0,0,1.375,0.56954],"texture":"#4"},"east":{"uv":[4.5,1,10,1.56954],"texture":"#4"},"south":{"uv":[0,0,1.375,0.56954],"texture":"#4"},"west":{"uv":[0,0,0,0],"texture":"#4"},"up":{"uv":[0,0,0,0],"texture":"#4"},"down":{"uv":[0,0,0,0],"texture":"#4"}}},{"name":"octagon","from":[7.39844,9.31333,10.41016],"to":[8.60156,9.81167,14.27734],"shade":false,"rotation":{"angle":-22.5,"axis":"z","origin":[8,9.5625,12.81641]},"faces":{"north":{"uv":[0,0,1.375,0.56954],"texture":"#4"},"east":{"uv":[4.5,1,10,1.56954],"texture":"#4"},"south":{"uv":[0,0,1.375,0.56954],"texture":"#4"},"west":{"uv":[0,0,0,0],"texture":"#4"},"up":{"uv":[0,0,0,0],"texture":"#4"},"down":{"uv":[0,0,0,0],"texture":"#4"}}}],"display":{"thirdperson_righthand":{"translation":[0,1.5,-3.5],"scale":[0.55,0.55,0.55]},"thirdperson_lefthand":{"translation":[0,0.5,-4.25],"scale":[0.55,0.55,0.55]},"firstperson_righthand":{"translation":[-1,3,-8],"scale":[1.15,1.15,1.15]},"firstperson_lefthand":{"translation":[-4,2.25,-6.75]},"ground":{"scale":[0.55,0.55,0.55]},"gui":{"rotation":[30,-145,0],"scale":[0.5,0.5,0.5]},"fixed":{"rotation":[0,90,0],"translation":[-1,1,-2],"scale":[1.1,1.1,1.1]}},"groups":[{"name":"bolt","origin":[8,15.64063,16.95313],"color":0,"children":[{"name":"octagon","origin":[8,8,8],"color":0,"children":[0,1,2,3]}]}]}